setuptools_git_versioning/__init__.py
setuptools_git_versioning/__main__.py
setuptools_git_versioning/cli.py
setuptools_git_versioning/defaults.py
setuptools_git_versioning/factories.py
setuptools_git_versioning/git.py
setuptools_git_versioning/log.py
setuptools_git_versioning/setup.py
setuptools_git_versioning/subst.py
setuptools_git_versioning/version.py
setuptools_git_versioning-3.0.0.dist-info/licenses/LICENSE
setuptools_git_versioning-3.0.0.dist-info/METADATA
setuptools_git_versioning-3.0.0.dist-info/WHEEL
setuptools_git_versioning-3.0.0.dist-info/entry_points.txt
setuptools_git_versioning-3.0.0.dist-info/top_level.txt
setuptools_git_versioning-3.0.0.dist-info/RECORD
