Metadata-Version: 2.4
Name: setuptools-git-versioning
Version: 3.0.0
Summary: Use git repo data for building a version number according to PEP-440
Author-email: dolfinus <martinov.m.s.8@gmail.com>
License: MIT
Project-URL: Homepage, https://setuptools-git-versioning.readthedocs.io
Project-URL: Documentation, https://setuptools-git-versioning.readthedocs.io
Project-URL: Source, https://github.com/dolfinus/setuptools-git-versioning
Project-URL: CI/CD, https://github.com/dolfinus/setuptools-git-versioning/actions
Project-URL: Coverage, https://app.codecov.io/gh/dolfinus/setuptools-git-versioning
Project-URL: Tracker, https://github.com/dolfinus/setuptools-git-versioning/issues
Keywords: setuptools,git,versioning,pep-440
Classifier: Framework :: Setuptools Plugin
Classifier: Intended Audience :: Developers
Classifier: Programming Language :: Python :: 3 :: Only
Classifier: Programming Language :: Python :: 3.7
Classifier: Programming Language :: Python :: 3.8
Classifier: Programming Language :: Python :: 3.9
Classifier: Programming Language :: Python :: 3.10
Classifier: Programming Language :: Python :: 3.11
Classifier: Programming Language :: Python :: 3.12
Classifier: Programming Language :: Python :: 3.13
Classifier: Operating System :: OS Independent
Requires-Python: >=3.7
License-File: LICENSE
Requires-Dist: packaging
Requires-Dist: setuptools
Requires-Dist: tomli>=2.0.1; python_version < "3.11"
Dynamic: license-file
